pyown/__init__.py
pyown/exceptions.py
pyown/py.typed
pyown/auth/__init__.py
pyown/auth/enum.py
pyown/auth/hmac.py
pyown/auth/open.py
pyown/client/__init__.py
pyown/client/base.py
pyown/client/client.py
pyown/client/session.py
pyown/items/__init__.py
pyown/items/base.py
pyown/items/utils.py
pyown/items/automation/__init__.py
pyown/items/automation/automation.py
pyown/items/camera/__init__.py
pyown/items/camera/camera.py
pyown/items/energy/__init__.py
pyown/items/energy/dataclass.py
pyown/items/energy/energy.py
pyown/items/energy/enums.py
pyown/items/energy/stop_go.py
pyown/items/gateway/__init__.py
pyown/items/gateway/gateway.py
pyown/items/lighting/__init__.py
pyown/items/lighting/base.py
pyown/items/lighting/dimmer.py
pyown/items/lighting/light.py
pyown/items/temperature/__init__.py
pyown/messages/__init__.py
pyown/messages/ack.py
pyown/messages/base.py
pyown/messages/dimension.py
pyown/messages/nack.py
pyown/messages/normal.py
pyown/messages/status.py
pyown/protocol/__init__.py
pyown/protocol/protocol.py
pyown/tags/__init__.py
pyown/tags/base.py
pyown/tags/dimension.py
pyown/tags/what.py
pyown/tags/where.py
pyown/tags/who.py
pyown-0.4.1.dist-info/METADATA
pyown-0.4.1.dist-info/WHEEL
pyown-0.4.1.dist-info/licenses/LICENSE
pyown-0.4.1.dist-info/RECORD
