Metadata-Version: 2.4
Name: pyown
Version: 0.4.1
Summary: Python wrapper for OpenWebNet protocol
Project-URL: repository, https://github.com/jotonedev/pyown
Project-URL: documentation, https://jotonedev.github.io/pyown/
Author-email: John Toniutti <john.toniutti@gmail.com>
License-Expression: GPL-3.0-or-later
License-File: LICENSE
Keywords: bticino,legrand,myhome,openwebnet
Classifier: Development Status :: 4 - Beta
Classifier: Intended Audience :: Developers
Classifier: Programming Language :: Python :: 3
Classifier: Programming Language :: Python :: 3.11
Classifier: Programming Language :: Python :: 3.12
Classifier: Programming Language :: Python :: 3.13
Classifier: Programming Language :: Python :: 3.14
Classifier: Topic :: Home Automation
Classifier: Topic :: Software Development :: Libraries :: Python Modules
Classifier: Typing :: Typed
Requires-Python: >=3.11.4
